fitbit/__init__.py
fitbit/api.py
fitbit/exceptions.py
fitbit/utils.py
fitbit-0.2.2.dist-info/DESCRIPTION.rst
fitbit-0.2.2.dist-info/METADATA
fitbit-0.2.2.dist-info/metadata.json
fitbit-0.2.2.dist-info/RECORD
fitbit-0.2.2.dist-info/top_level.txt
fitbit-0.2.2.dist-info/WHEEL
