Metadata-Version: 1.1
Name: fitbit
Version: 0.2.2
Summary: Fitbit API Wrapper.
Home-page: https://github.com/orcasgit/python-fitbit
Author: Issac Kelly and ORCAS
Author-email: bpitcher@orcasinc.com
License: Apache 2.0
Platform: UNKNOWN
Classifier: Intended Audience :: Developers
Classifier: Natural Language :: English
Classifier: License :: OSI Approved :: Apache Software License
Classifier: Programming Language :: Python
Classifier: Programming Language :: Python :: 2.7
Classifier: Programming Language :: Python :: 3
Classifier: Programming Language :: Python :: 3.3
Classifier: Programming Language :: Python :: 3.4
Classifier: Programming Language :: Python :: 3.5
Classifier: Programming Language :: Python :: Implementation :: PyPy
